{"errors":[],"warnings":[],"namedChunkGroups":{"polyfill":{"chunks":[6,12],"assets":["webpack-runtime-7b749663576b9453b595.js","webpack-runtime-7b749663576b9453b595.js.map","polyfill-a1fb6f2fc2cfb8d79ec1.js","polyfill-a1fb6f2fc2cfb8d79ec1.js.map"],"children":{},"childAssets":{}},"app":{"chunks":[6,0,4,7],"assets":["webpack-runtime-7b749663576b9453b595.js","webpack-runtime-7b749663576b9453b595.js.map","styles.47775eafa95b50dfe0fc.css","styles-89fd2ae28bdf06750a71.js","styles-89fd2ae28bdf06750a71.js.map","framework-fcdc86b0b674a2ae7ac6.js","framework-fcdc86b0b674a2ae7ac6.js.map","app-2c683bf3aa006c76e612.js","app-2c683bf3aa006c76e612.js.map"],"children":{},"childAssets":{}},"component---src-pages-404-js":{"chunks":[0,1,2,3,8],"assets":["styles.47775eafa95b50dfe0fc.css","styles-89fd2ae28bdf06750a71.js","styles-89fd2ae28bdf06750a71.js.map","1bfc9850-90fffb503faae84ffd54.js","1bfc9850-90fffb503faae84ffd54.js.map","95b64a6e-7ad6393d20fce70e6591.js","95b64a6e-7ad6393d20fce70e6591.js.map","commons-897a665d59872a1ca387.js","commons-897a665d59872a1ca387.js.map","component---src-pages-404-js-7a44afd693061778f6be.js","component---src-pages-404-js-7a44afd693061778f6be.js.map"],"children":{},"childAssets":{}},"component---src-pages-index-js":{"chunks":[0,4,1,2,3,5,9],"assets":["styles.47775eafa95b50dfe0fc.css","styles-89fd2ae28bdf06750a71.js","styles-89fd2ae28bdf06750a71.js.map","framework-fcdc86b0b674a2ae7ac6.js","framework-fcdc86b0b674a2ae7ac6.js.map","1bfc9850-90fffb503faae84ffd54.js","1bfc9850-90fffb503faae84ffd54.js.map","95b64a6e-7ad6393d20fce70e6591.js","95b64a6e-7ad6393d20fce70e6591.js.map","commons-897a665d59872a1ca387.js","commons-897a665d59872a1ca387.js.map","fd180c1b2af7c7058ca7f29111b44de3449c636a-befebd592ba470aeb8ab.js","fd180c1b2af7c7058ca7f29111b44de3449c636a-befebd592ba470aeb8ab.js.map","component---src-pages-index-js-a79b2240e892b2003186.js","component---src-pages-index-js-a79b2240e892b2003186.js.map"],"children":{},"childAssets":{}},"component---src-templates-blog-js":{"chunks":[0,1,2,3,10],"assets":["styles.47775eafa95b50dfe0fc.css","styles-89fd2ae28bdf06750a71.js","styles-89fd2ae28bdf06750a71.js.map","1bfc9850-90fffb503faae84ffd54.js","1bfc9850-90fffb503faae84ffd54.js.map","95b64a6e-7ad6393d20fce70e6591.js","95b64a6e-7ad6393d20fce70e6591.js.map","commons-897a665d59872a1ca387.js","commons-897a665d59872a1ca387.js.map","component---src-templates-blog-js-3c80630445d21ebec98f.js","component---src-templates-blog-js-3c80630445d21ebec98f.js.map"],"children":{},"childAssets":{}},"component---src-templates-page-js":{"chunks":[0,4,1,2,3,5,11],"assets":["styles.47775eafa95b50dfe0fc.css","styles-89fd2ae28bdf06750a71.js","styles-89fd2ae28bdf06750a71.js.map","framework-fcdc86b0b674a2ae7ac6.js","framework-fcdc86b0b674a2ae7ac6.js.map","1bfc9850-90fffb503faae84ffd54.js","1bfc9850-90fffb503faae84ffd54.js.map","95b64a6e-7ad6393d20fce70e6591.js","95b64a6e-7ad6393d20fce70e6591.js.map","commons-897a665d59872a1ca387.js","commons-897a665d59872a1ca387.js.map","fd180c1b2af7c7058ca7f29111b44de3449c636a-befebd592ba470aeb8ab.js","fd180c1b2af7c7058ca7f29111b44de3449c636a-befebd592ba470aeb8ab.js.map","component---src-templates-page-js-e0a39f7162c53a3807c8.js","component---src-templates-page-js-e0a39f7162c53a3807c8.js.map"],"children":{},"childAssets":{}}},"assetsByChunkName":{"polyfill":["webpack-runtime-7b749663576b9453b595.js","polyfill-a1fb6f2fc2cfb8d79ec1.js"],"app":["webpack-runtime-7b749663576b9453b595.js","styles.47775eafa95b50dfe0fc.css","styles-89fd2ae28bdf06750a71.js","framework-fcdc86b0b674a2ae7ac6.js","app-2c683bf3aa006c76e612.js"],"component---src-pages-404-js":["styles.47775eafa95b50dfe0fc.css","styles-89fd2ae28bdf06750a71.js","1bfc9850-90fffb503faae84ffd54.js","95b64a6e-7ad6393d20fce70e6591.js","commons-897a665d59872a1ca387.js","component---src-pages-404-js-7a44afd693061778f6be.js"],"component---src-pages-index-js":["styles.47775eafa95b50dfe0fc.css","styles-89fd2ae28bdf06750a71.js","framework-fcdc86b0b674a2ae7ac6.js","1bfc9850-90fffb503faae84ffd54.js","95b64a6e-7ad6393d20fce70e6591.js","commons-897a665d59872a1ca387.js","fd180c1b2af7c7058ca7f29111b44de3449c636a-befebd592ba470aeb8ab.js","component---src-pages-index-js-a79b2240e892b2003186.js"],"component---src-templates-blog-js":["styles.47775eafa95b50dfe0fc.css","styles-89fd2ae28bdf06750a71.js","1bfc9850-90fffb503faae84ffd54.js","95b64a6e-7ad6393d20fce70e6591.js","commons-897a665d59872a1ca387.js","component---src-templates-blog-js-3c80630445d21ebec98f.js"],"component---src-templates-page-js":["styles.47775eafa95b50dfe0fc.css","styles-89fd2ae28bdf06750a71.js","framework-fcdc86b0b674a2ae7ac6.js","1bfc9850-90fffb503faae84ffd54.js","95b64a6e-7ad6393d20fce70e6591.js","commons-897a665d59872a1ca387.js","fd180c1b2af7c7058ca7f29111b44de3449c636a-befebd592ba470aeb8ab.js","component---src-templates-page-js-e0a39f7162c53a3807c8.js"]}}